mongodb_connect/__init__.py
mongodb_connect/mongo_crud.py
mongodbconnecterpkg-0.0.3.dist-info/METADATA
mongodbconnecterpkg-0.0.3.dist-info/WHEEL
mongodbconnecterpkg-0.0.3.dist-info/top_level.txt
mongodbconnecterpkg-0.0.3.dist-info/RECORD
